handlebars/__init__.py
handlebars/_compiler.py
handlebars/_templates/__init__.py
python_handlebars-0.0.3.dist-info/LICENSE
python_handlebars-0.0.3.dist-info/METADATA
python_handlebars-0.0.3.dist-info/WHEEL
python_handlebars-0.0.3.dist-info/top_level.txt
python_handlebars-0.0.3.dist-info/RECORD
