Metadata-Version: 2.1
Name: python-handlebars
Version: 0.0.3
Summary: Handlebars.js templating for Python 3
Author-email: wbond <will@wbond.net>, mjumbewu <mjumbewu@gmail.com>, hugobessa <hugo@vinta.com.br>
Project-URL: Documentation, https://github.com/vintasoftware/python-handlebars
Project-URL: Issues, https://github.com/vintasoftware/python-handlebars/issues
Project-URL: Source, https://github.com/vintasoftware/python-handlebars
Classifier: Development Status :: 4 - Beta
Classifier: Intended Audience :: Developers
Classifier: License :: OSI Approved :: GNU Library or Lesser General Public License (LGPL)
Classifier: Operating System :: OS Independent
Classifier: Programming Language :: Python :: 3
Classifier: Programming Language :: Python :: 3.8
Classifier: Programming Language :: Python :: 3.9
Classifier: Programming Language :: Python :: 3.10
Classifier: Programming Language :: Python :: 3.11
Classifier: Programming Language :: Python :: 3.12
Classifier: Programming Language :: Python :: 3.13
Requires-Python: >=3.8
License-File: LICENSE
Requires-Dist: python-ometa >=0.0.1
